sequential-circuits/D-flipflop/dff.v
`timescale 1ns/1ps

module dff(
			input wire D,		// input D
			input wire clk,		// input clk
			input wire rstn,	// reset (active low)
			output reg Q,		// output
			output wire Qb		// complementary output
		);

	assign Qb = ~Q;	
		
	always @(posedge clk ,posedge rstn) begin
		if(rstn) begin
			Q = 0;
		end
		else begin
			Q = D;
		end		
	end
endmodule

sequential-circuits/D-flipflop/tb.v
`timescale 1ns/1ps

module dff_tb();
			reg D;		// input D
			reg clk;		// input clk
			reg rstn;	// reset (active low)
			wire Q;		// output
			wire Qb;		// complementary output
    
	// clock generation block
	initial begin
		clk = 0;
		forever begin
			#10 clk = ~clk;
		end // forever
	end	

	// Test block
	initial begin
        rstn = 1;
		
		#40;
        rstn = 0;
		D = 0;
		#20;
		D = 1;
        #20;
		D = 0;
        #20;
		D = 1;
        #20;
		D = 0;
	end // initial

	// monitor results
	initial begin
		$monitor("@:%0t :: rstn:%0b, D:%0b, Q:%0b, Qb:%0b", $time, rstn, D, Q, Qb);
	end	

	// finish simulation
	initial begin
		# 1000;
		$finish();
	end // initial
    initial begin
        $dumpfile("dff.vcd");
        $dumpvars(1);
    end
    // Instantiation of DUT
    dff D_DUT(
    			.D(D),
    			.clk(clk),
    			.rstn(rstn),
    			.Q(Q),
    			.Qb(Qb)
    	);
endmodule

sequential-circuits/D-flipflop/dff.vcd
$date
	Fri Nov 05 16:45:36 2021
$end
$version
	Icarus Verilog
$end
$timescale
	1ps
$end
$scope module dff_tb $end
$var wire 1 ! Qb $end
$var wire 1 " Q $end
$var reg 1 # D $end
$var reg 1 $ clk $end
$var reg 1 % rstn $end
$upscope $end
$enddefinitions $end
#0
$dumpvars
1%
0$
x#
0"
1!
$end
#10000
1$
#20000
0$
#30000
1$
#40000
0$
0#
0%
#50000
1$
#60000
0$
1#
#70000
0!
1"
1$
#80000
0$
0#
#90000
1!
0"
1$
#100000
0$
1#
#110000
0!
1"
1$
#120000
0$
0#
#130000
1!
0"
1$
